selectpdf.py
selectpdf-1.4.0.dist-info/LICENSE
selectpdf-1.4.0.dist-info/METADATA
selectpdf-1.4.0.dist-info/WHEEL
selectpdf-1.4.0.dist-info/top_level.txt
selectpdf-1.4.0.dist-info/RECORD
