Metadata-Version: 2.1
Name: selectpdf
Version: 1.4.0
Summary: Python client for SelectPdf Online REST API
Home-page: https://github.com/selectpdf/selectpdf-api-python-client
Author: SelectPdf
Author-email: support@selectpdf.com
License: License :: OSI Approved :: MIT License
Platform: UNKNOWN
Classifier: Programming Language :: Python :: 2
Classifier: Programming Language :: Python :: 3
Classifier: License :: OSI Approved :: MIT License
Classifier: Operating System :: OS Independent
Classifier: Intended Audience :: Developers
Classifier: Topic :: Software Development :: Libraries
